hanmatek_cli/__init__.py
hanmatek_cli/__main__.py
hanmatek_cli/py.typed
hanmatek_cli-0.0.0.dist-info/entry_points.txt
hanmatek_cli-0.0.0.dist-info/LICENSE.rst
hanmatek_cli-0.0.0.dist-info/WHEEL
hanmatek_cli-0.0.0.dist-info/METADATA
hanmatek_cli-0.0.0.dist-info/RECORD
