Metadata-Version: 2.1
Name: hanmatek-cli
Version: 0.0.0
Summary: HANMATEK Power Supplies (HM305, HM310, HM310p, RS605p)
Home-page: https://github.com/5H3LL3H5/hanmatek-cli
License: MIT
Author: Christian Stenzel
Author-email: christianstenzel@linux.com
Requires-Python: >=3.6.1,<4.0.0
Classifier: License :: OSI Approved :: MIT License
Classifier: Programming Language :: Python :: 3
Classifier: Programming Language :: Python :: 3.6
Classifier: Programming Language :: Python :: 3.7
Classifier: Programming Language :: Python :: 3.8
Classifier: Programming Language :: Python :: 3.9
Requires-Dist: click (>=7.0,<8.0)
Project-URL: Changelog, https://github.com/5H3LL3H5/hanmatek-cli/releases
Project-URL: Documentation, https://hanmatek-cli.readthedocs.io
Project-URL: Repository, https://github.com/5H3LL3H5/hanmatek-cli
